README.txt
setup.py
pokestarfansloggingsetup/__init__.py
pokestarfansloggingsetup.egg-info/PKG-INFO
pokestarfansloggingsetup.egg-info/SOURCES.txt
pokestarfansloggingsetup.egg-info/dependency_links.txt
pokestarfansloggingsetup.egg-info/top_level.txt
pokestarfansloggingsetup.egg-info/zip-safe