Metadata-Version: 1.0
Name: pokestarfansloggingsetup
Version: 2.0.1
Summary: My logging setup. Dependency
Home-page: https://pypi.python.org/pypi/pokestarfansloggingsetup
Author: PokestarFan
Author-email: pokestarfan@yahoo.com
License: MIT
Platform: UNKNOWN
